fastapi_sysunicorns/__init__.py
fastapi_sysunicorns/version.py
fastapi_sysunicorns_helper-1.3.6.dist-info/LICENSE
fastapi_sysunicorns_helper-1.3.6.dist-info/METADATA
fastapi_sysunicorns_helper-1.3.6.dist-info/WHEEL
fastapi_sysunicorns_helper-1.3.6.dist-info/top_level.txt
fastapi_sysunicorns_helper-1.3.6.dist-info/RECORD
