Metadata-Version: 2.1
Name: fastapi-sysunicorns-helper
Version: 1.3.6
Summary: Utility Package for FastApi Python Application
Home-page: https://github.com/public-sysunicorns-info/fastapi_sysunicorns_helper
Author: miragecentury
Author-email: victorien.vanroye@gmail.com
License: UNKNOWN
Project-URL: Bug Tracker, https://github.com/public-sysunicorns-info/fastapi_sysunicorns_helper/issues
Platform: UNKNOWN
Classifier: Programming Language :: Python :: 3
Classifier: License :: OSI Approved :: MIT License
Classifier: Operating System :: OS Independent
Requires-Python: >=3.9
License-File: LICENSE
Requires-Dist: pydantic (<2.0.0,>=1.9.0)
Requires-Dist: fastapi (<1.0.0,>=0.73.0)
Requires-Dist: dependency-injector (<5.0,>=4.0)
